public class com.go.gl.util.FastQueue {
  public com.go.gl.util.FastQueue(int);
    Code:
       0: aload_0       
       1: invokespecial #16                 // Method java/lang/Object."<init>":()V
       4: iload_1       
       5: ifge          16
       8: new           #18                 // class java/lang/IllegalArgumentException
      11: dup           
      12: invokespecial #19                 // Method java/lang/IllegalArgumentException."<init>":()V
      15: athrow        
      16: bipush        16
      18: istore_2      
      19: iload_2       
      20: iload_1       
      21: if_icmplt     53
      24: aload_0       
      25: iload_2       
      26: anewarray     #4                  // class java/lang/Object
      29: putfield      #21                 // Field a:[Ljava/lang/Object;
      32: aload_0       
      33: aload_0       
      34: getfield      #21                 // Field a:[Ljava/lang/Object;
      37: arraylength   
      38: putfield      #23                 // Field b:I
      41: aload_0       
      42: bipush        -1
      44: aload_0       
      45: getfield      #23                 // Field b:I
      48: iadd          
      49: putfield      #25                 // Field c:I
      52: return        
      53: iload_2       
      54: iconst_1      
      55: ishl          
      56: istore_2      
      57: goto          19

  public void cleanup();
    Code:
       0: aload_0       
       1: getfield      #21                 // Field a:[Ljava/lang/Object;
       4: aconst_null   
       5: invokestatic  #32                 // Method java/util/Arrays.fill:([Ljava/lang/Object;Ljava/lang/Object;)V
       8: aload_0       
       9: iconst_0      
      10: putfield      #34                 // Field e:I
      13: aload_0       
      14: iconst_0      
      15: putfield      #36                 // Field d:I
      18: return        

  protected void handleOverflow(java.lang.Object);
    Code:
       0: return        

  public final boolean isEmpty();
    Code:
       0: aload_0       
       1: getfield      #36                 // Field d:I
       4: aload_0       
       5: getfield      #34                 // Field e:I
       8: if_icmpne     15
      11: iconst_1      
      12: istore_1      
      13: iload_1       
      14: ireturn       
      15: iconst_0      
      16: istore_1      
      17: goto          13

  public final java.lang.Object popFront();
    Code:
       0: aconst_null   
       1: astore_1      
       2: aload_0       
       3: getfield      #34                 // Field e:I
       6: istore_2      
       7: aload_0       
       8: getfield      #36                 // Field d:I
      11: istore_3      
      12: iload_2       
      13: iload_3       
      14: if_icmpne     19
      17: aload_1       
      18: areturn       
      19: iload_3       
      20: iconst_1      
      21: iadd          
      22: aload_0       
      23: getfield      #25                 // Field c:I
      26: iand          
      27: istore        4
      29: aload_0       
      30: getfield      #21                 // Field a:[Ljava/lang/Object;
      33: iload_3       
      34: aaload        
      35: astore        5
      37: aload_0       
      38: getfield      #21                 // Field a:[Ljava/lang/Object;
      41: iload_3       
      42: aconst_null   
      43: aastore       
      44: aload_0       
      45: iload         4
      47: putfield      #36                 // Field d:I
      50: aload         5
      52: astore_1      
      53: goto          17

  public final void process(com.go.gl.util.FastQueue$Processor);
    Code:
       0: aload_0       
       1: getfield      #34                 // Field e:I
       4: istore_2      
       5: aload_0       
       6: getfield      #36                 // Field d:I
       9: istore_3      
      10: iload_2       
      11: iload_3       
      12: if_icmpne     16
      15: return        
      16: iload_3       
      17: iconst_1      
      18: iadd          
      19: aload_0       
      20: getfield      #25                 // Field c:I
      23: iand          
      24: istore        4
      26: iload_3       
      27: iload_2       
      28: if_icmpeq     15
      31: aload_0       
      32: getfield      #21                 // Field a:[Ljava/lang/Object;
      35: iload_3       
      36: aaload        
      37: astore        5
      39: aload_0       
      40: getfield      #21                 // Field a:[Ljava/lang/Object;
      43: iload_3       
      44: aconst_null   
      45: aastore       
      46: aload_0       
      47: iload         4
      49: putfield      #36                 // Field d:I
      52: iload         4
      54: iconst_1      
      55: iadd          
      56: aload_0       
      57: getfield      #25                 // Field c:I
      60: iand          
      61: istore        6
      63: aload_1       
      64: aload         5
      66: invokeinterface #48,  2           // InterfaceMethod com/go/gl/util/FastQueue$Processor.process:(Ljava/lang/Object;)V
      71: iload         4
      73: istore_3      
      74: iload         6
      76: istore        4
      78: goto          26

  public final boolean pushBack(java.lang.Object);
    Code:
       0: aload_0       
       1: getfield      #36                 // Field d:I
       4: istore_2      
       5: aload_0       
       6: getfield      #34                 // Field e:I
       9: istore_3      
      10: iload_3       
      11: iconst_1      
      12: iadd          
      13: aload_0       
      14: getfield      #25                 // Field c:I
      17: iand          
      18: istore        4
      20: iload         4
      22: iload_2       
      23: if_icmpne     37
      26: aload_0       
      27: aload_1       
      28: invokevirtual #52                 // Method handleOverflow:(Ljava/lang/Object;)V
      31: iconst_0      
      32: istore        5
      34: iload         5
      36: ireturn       
      37: aload_0       
      38: getfield      #21                 // Field a:[Ljava/lang/Object;
      41: iload_3       
      42: aload_1       
      43: aastore       
      44: aload_0       
      45: iload         4
      47: putfield      #34                 // Field e:I
      50: iconst_1      
      51: istore        5
      53: goto          34

  public boolean remove(java.lang.Object);
    Code:
       0: iconst_0      
       1: istore_2      
       2: aload_0       
       3: getfield      #34                 // Field e:I
       6: istore_3      
       7: aload_0       
       8: getfield      #36                 // Field d:I
      11: istore        4
      13: iload_3       
      14: iload         4
      16: if_icmpne     21
      19: iload_2       
      20: ireturn       
      21: iload         4
      23: iconst_1      
      24: iadd          
      25: aload_0       
      26: getfield      #25                 // Field c:I
      29: iand          
      30: istore        5
      32: iload         4
      34: iload_3       
      35: if_icmpeq     19
      38: aload_0       
      39: getfield      #21                 // Field a:[Ljava/lang/Object;
      42: iload         4
      44: aaload        
      45: aload_1       
      46: if_acmpne     62
      49: aload_0       
      50: getfield      #21                 // Field a:[Ljava/lang/Object;
      53: iload         4
      55: aconst_null   
      56: aastore       
      57: iconst_1      
      58: istore_2      
      59: goto          19
      62: iload         5
      64: iconst_1      
      65: iadd          
      66: aload_0       
      67: getfield      #25                 // Field c:I
      70: iand          
      71: istore        6
      73: iload         5
      75: istore        4
      77: iload         6
      79: istore        5
      81: goto          32
}
